LICENSE
backend_library_common/__init__.py
backend_library_common/utils/__init__.py
backend_library_common/utils/main.py
backend_library_common/utils/params.py
backend_library_common-0.1.5.dist-info/LICENSE
backend_library_common-0.1.5.dist-info/WHEEL
backend_library_common-0.1.5.dist-info/METADATA
backend_library_common-0.1.5.dist-info/RECORD
